MANIFEST.in
README.rst
setup.cfg
setup.py
jars/spark-api-uber.jar
sourced/__init__.py
sourced/spark/__init__.py
sourced/spark/api.py
sourced_spark_api.egg-info/PKG-INFO
sourced_spark_api.egg-info/SOURCES.txt
sourced_spark_api.egg-info/dependency_links.txt
sourced_spark_api.egg-info/requires.txt
sourced_spark_api.egg-info/top_level.txt
test/test_api.py
test/test_sourced_dataframe.py