Metadata-Version: 1.1
Name: sourced-spark-api
Version: 0.0.1
Summary: API to use Spark on top of source code repositories.
Home-page: https://github.com/src-d/spark-api/tree/master/python
Author: source{d}
Author-email: hello@sourced.tech
License: Apache-2.0
Platform: UNKNOWN
Classifier: Development Status :: 2 - Pre-Alpha
Classifier: Intended Audience :: Developers
Classifier: License :: OSI Approved :: Apache Software License
Classifier: Topic :: Scientific/Engineering :: Information Analysis
Classifier: Programming Language :: Python :: 2.7
Classifier: Programming Language :: Python :: 3
